algorithms/__init__.py
data_structures/__init__.py
data_structures/linked_list.py
data_structures/node.py
data_structures/queue.py
data_structures/rotation_linked_list.py
data_structures/rotation_queue.py
data_structures/rotation_stack.py
data_structures/stack.py
ninja_utilities-0.1.1.dist-info/licenses/LICENSE
ninja_utilities-0.1.1.dist-info/METADATA
ninja_utilities-0.1.1.dist-info/WHEEL
ninja_utilities-0.1.1.dist-info/top_level.txt
ninja_utilities-0.1.1.dist-info/RECORD
