Metadata-Version: 2.4
Name: ninja-utilities
Version: 0.1.1
Summary: Python Data Structure Package
Author-email: Fabio Antonio Astore <astore.a.fabio@gmail.com>
License: MIT License
License-File: LICENSE
Dynamic: license-file
